cv2filters/__init__.py
cv2filters/image_filters.py
cv2filters/video_filters.py
cv2filters-0.2.6.dist-info/LICENSE
cv2filters-0.2.6.dist-info/METADATA
cv2filters-0.2.6.dist-info/WHEEL
cv2filters-0.2.6.dist-info/top_level.txt
cv2filters-0.2.6.dist-info/RECORD
