Metadata-Version: 2.1
Name: cv2filters
Version: 0.2.6
Summary: Unleash the power of OpenCV with CV2Filters, the ultimate image processing wrapper for all skill levels, revolutionizing computer vision with seamless exploration, manipulation, and groundbreaking research
Home-page: https://github.com/nuhmanpk/cv2filters
Author: Nuhman Pk
Author-email: nuhmanpk7@gmail.com
License: MIT
Platform: UNKNOWN
Classifier: Programming Language :: Python :: 3
Classifier: Programming Language :: Python :: 3.6
Classifier: Programming Language :: Python :: 3.7
Classifier: Programming Language :: Python :: 3.8
Classifier: Programming Language :: Python :: 3.9
Classifier: License :: OSI Approved :: MIT License
Classifier: Operating System :: OS Independent
Requires-Python: >=3.6
License-File: LICENSE
Requires-Dist: opencv-python
Requires-Dist: matplotlib
